[[{"__type__":"cc.SceneAsset","_name":"GameOver","scene":{"__id__":1},"asyncLoadAssets":null},{"__type__":"cc.Scene","_name":"New Node","_children":[{"__id__":2},{"__id__":3},{"__id__":4}],"_anchorPoint":{"__type__":"cc.Vec2"},"autoReleaseAssets":false},{"__type__":"cc.Node","_name":"Canvas","_parent":{"__id__":1},"_components":[{"__type__":"cc.Canvas","node":{"__id__":2}}],"_id":"51mQkua6dCQ53gSC4RYMRg","_position":{"__type__":"cc.Vec2","x":480,"y":320}},{"__type__":"cc.Node","_name":"label","_parent":{"__id__":1},"_components":[{"__type__":"cc.Label","node":{"__id__":3},"_useOriginalSize":false,"_actualFontSize":120,"_fontSize":120,"_lineHeight":100,"_N$string":"Game Over","_N$horizontalAlign":1,"_N$verticalAlign":1}],"_id":"0ekFi3IF5Ji5X6AChLAqpV","_contentSize":{"__type__":"cc.Size","width":620,"height":100},"_position":{"__type__":"cc.Vec2","x":478,"y":305}},{"__type__":"cc.Node","_name":"gameOver","_parent":{"__id__":1},"_components":[{"__type__":"cc.Sprite","node":{"__id__":4},"_spriteFrame":{"__uuid__":"fbR2fMvtpBxaWCQLuI2aHW"}}],"_id":"1fwb7QZnJFqZxSso/U5u/i","_contentSize":{"__type__":"cc.Size","width":3200,"height":2560},"_scaleX":0.7,"_scaleY":0.7,"_position":{"__type__":"cc.Vec2","x":479,"y":317}}],{"__type__":"cc.SpriteFrame","content":{"name":"gameOver","texture":"beGvTkfwNCoq/86PN/wktW","rect":[0,0,3200,2560],"offset":[0,0],"originalSize":[3200,2560]}}]